{"proportion_index": [0.634, 0.6906, 0.5845, 0.2612, 0.4139], "materialproperties": {}, "structural": {"Legs_UpperlegsTone": 0.47, "Feet_Mass": 0.74, "Arms_UpperarmTone": 0.62, "Arms_ForearmTone": 0.62, "Legs_LowerlegsMass": 1.24, "Torso_Vshape": 0.62, "Neck_Tone": 0.62, "Shoulders_Tone": 0.74, "Cheeks_Tone": 0.62, "Legs_UpperlegsMass": 0.92, "Waist_Size": 0.572, "Wrists_Size": 0.536, "Legs_UpperlegLength": 0.32, "Hands_Mass": 0.74, "Cheeks_Mass": 0.74, "Stomach_Volume": 0.5048, "Arms_UpperarmMass": 1.16, "Stomach_LocalFat": 0.5048, "Pelvis_GluteusTone": 0.62, "Shoulders_Mass": 0.86, "Legs_LowerlegLength": 0.39, "Head_Size": 0.59, "Torso_SizeX": 0.47, "Torso_Tone": 0.65, "Torso_Mass": 0.98, "Pelvis_GluteusMass": 0.95, "Abdomen_Mass": 0.74, "Legs_KneeSize": 1.072, "Legs_LowerlegsTone": 1.07, "Neck_Mass": 0.74, "Abdomen_Tone": 0.62, "Arms_ForearmMass": 1.24}, "metaproperties": {"last_character_age": 0.0, "last_character_mass": 0.24, "character_age": 0.0, "character_mass": 0.24, "last_character_tone": 0.12, "character_tone": 0.12}, "manuellab_vers": [1, 6, 0]}