{"proportion_index": [0.6224, 0.5574, 0.5434, 0.2121, 0.3511], "structural": {"Torso_BreastTone": 0.548, "Legs_UpperlegLength": 0.08, "Abdomen_Tone": 0.26, "Cheeks_Tone": 0.26, "Shoulders_Tone": 0.26, "Waist_Size": 0.8576, "Legs_UpperlegsTone": 0.26, "Torso_Length": 0.68, "Legs_LowerlegsTone": 0.26, "Shoulders_Length": 0.65, "Torso_SizeX": 0.83, "Shoulders_Mass": 0.56, "Torso_Tone": 0.26, "Torso_BreastMass": 0.0, "Arms_UpperarmTone": 0.26, "Torso_Vshape": 0.29, "Pelvis_GluteusTone": 0.26, "Stomach_Volume": 0.56, "Arms_ForearmTone": 0.26, "Wrists_Size": 0.488, "Pelvis_SizeX": 0.32, "Neck_Tone": 0.26}, "manuellab_vers": [1, 6, 0], "metaproperties": {"last_character_age": 0.0, "character_tone": -0.24, "last_character_mass": 0.0, "character_mass": 0.0, "character_age": 0.0, "last_character_tone": -0.24}, "materialproperties": {}}